relaystory/__init__.py
relaystory/__version__.py
relaystory/relaystory.py
relaystory-0.2.0.dist-info/LICENSE
relaystory-0.2.0.dist-info/METADATA
relaystory-0.2.0.dist-info/WHEEL
relaystory-0.2.0.dist-info/entry_points.txt
relaystory-0.2.0.dist-info/top_level.txt
relaystory-0.2.0.dist-info/RECORD
