Metadata-Version: 2.1
Name: relaystory
Version: 0.2.0
Summary: A Framework for Multi-branch Relay Story
Home-page: https://github.com/BobAnkh/relay-story
Author: BobAnkh
Author-email: bobankhshen@gmail.com
License: Apache 2.0
Keywords: relay,story,framework,BobAnkh,multi-branch
Platform: any
Classifier: Programming Language :: Python :: 3
Classifier: Environment :: Console
Classifier: License :: OSI Approved :: Apache Software License
Classifier: Operating System :: OS Independent
Requires-Python: >3
Requires-Dist: markdown
